[{"name":"multi_reg_exp","types":[{"name":"MultiRegExp","kind":"class","members":[{"kind":"constructor","noparams":true,"name":"MultiRegExp","link_name":""},{"kind":"method","name":"allMatches"},{"kind":"method","name":"allMatchesFromStringContainer"},{"kind":"method","name":"firstMatch"},{"kind":"constructor","name":"MultiRegExp.fromIterable","link_name":"fromIterable"},{"kind":"method","name":"hasMatch"},{"kind":"getter","noparams":true,"name":"isCaseSensitive"},{"kind":"getter","noparams":true,"name":"isMultiLine"},{"kind":"method","name":"matchAsPrefix"},{"kind":"getter","noparams":true,"name":"pattern"},{"kind":"field","name":"regExps"},{"kind":"method","name":"stringMatch"}]},{"name":"MultiRegExpIterable","kind":"class","members":[{"kind":"constructor","name":"MultiRegExpIterable","link_name":""},{"kind":"getter","noparams":true,"name":"current"},{"kind":"constructor","name":"MultiRegExpIterable.fromString","link_name":"fromString"},{"kind":"field","name":"input"},{"kind":"getter","noparams":true,"name":"iterator"},{"kind":"method","noparams":true,"name":"moveNext"},{"kind":"field","name":"multiRegExp"}]},{"name":"StringContainer","kind":"class","members":[{"kind":"constructor","name":"StringContainer","link_name":""},{"kind":"method","name":"allMatches"},{"kind":"method","name":"allMatchesFromMultiRegExp"},{"kind":"getter","noparams":true,"name":"string"}]}]},{"name":"mutable_string","types":[{"name":"MutableString","kind":"class","members":[{"kind":"constructor","name":"MutableString","link_name":""},{"kind":"method","name":"allMatches"},{"kind":"method","name":"allMatchesFromMultiRegExp"},{"kind":"method","name":"replacePart"},{"kind":"field","name":"string"},{"kind":"method","name":"substring"},{"kind":"method","noparams":true,"name":"trim"}]},{"name":"MutableStringMatch","kind":"class","members":[{"kind":"constructor","name":"MutableStringMatch","link_name":""},{"kind":"method","name":"operator []","link_name":"[]"},{"kind":"field","name":"end"},{"kind":"method","name":"group"},{"kind":"getter","noparams":true,"name":"groupCount"},{"kind":"method","name":"groups"},{"kind":"field","name":"input"},{"kind":"getter","noparams":true,"name":"lastIndex"},{"kind":"setter","name":"lastIndex","link_name":"lastIndex="},{"kind":"getter","noparams":true,"name":"pattern"},{"kind":"method","name":"replacePart"},{"kind":"field","name":"start"}]},{"name":"MutableStringMatchesIterable","kind":"class","members":[{"kind":"constructor","name":"MutableStringMatchesIterable","link_name":""},{"kind":"getter","noparams":true,"name":"current"},{"kind":"getter","noparams":true,"name":"iterator"},{"kind":"field","name":"lastIndex"},{"kind":"method","noparams":true,"name":"moveNext"},{"kind":"field","name":"mutableString"},{"kind":"field","name":"regExp"}]}]},{"name":"preprocessor","types":[{"name":"Preprocessor","kind":"class","members":[{"kind":"constructor","name":"Preprocessor","link_name":""},{"kind":"field","name":"errorSourceAhead"},{"kind":"method","name":"indent"},{"kind":"method","name":"process"},{"kind":"field","name":"regExpIfThen"},{"kind":"field","name":"singleLinesSupportedTypes"},{"kind":"field","name":"types"}]}]}]
